AUTHORS
LICENSE
MANIFEST.in
NOTICE
README.rst
setup.cfg
setup.py
Flask_Admix.egg-info/PKG-INFO
Flask_Admix.egg-info/SOURCES.txt
Flask_Admix.egg-info/dependency_links.txt
Flask_Admix.egg-info/not-zip-safe
Flask_Admix.egg-info/requires.txt
Flask_Admix.egg-info/top_level.txt
flask_admin/__init__.py
flask_admin/_backwards.py
flask_admin/_compat.py
flask_admin/actions.py
flask_admin/babel.py
flask_admin/base.py
flask_admin/consts.py
flask_admin/helpers.py
flask_admin/menu.py
flask_admin/tools.py
flask_admin/contrib/__init__.py
flask_admin/contrib/fileadmin/__init__.py
flask_admin/contrib/fileadmin/azure.py
flask_admin/contrib/geoa/__init__.py
flask_admin/contrib/geoa/fields.py
flask_admin/contrib/geoa/form.py
flask_admin/contrib/geoa/typefmt.py
flask_admin/contrib/geoa/view.py
flask_admin/contrib/geoa/widgets.py
flask_admin/contrib/peewee/__init__.py
flask_admin/contrib/peewee/ajax.py
flask_admin/contrib/peewee/filters.py
flask_admin/contrib/peewee/form.py
flask_admin/contrib/peewee/tools.py
flask_admin/contrib/peewee/view.py
flask_admin/contrib/pymongo/__init__.py
flask_admin/contrib/pymongo/filters.py
flask_admin/contrib/pymongo/tools.py
flask_admin/contrib/pymongo/typefmt.py
flask_admin/contrib/pymongo/view.py
flask_admin/contrib/sqla/__init__.py
flask_admin/contrib/sqla/ajax.py
flask_admin/contrib/sqla/fields.py
flask_admin/contrib/sqla/filters.py
flask_admin/contrib/sqla/form.py
flask_admin/contrib/sqla/tools.py
flask_admin/contrib/sqla/typefmt.py
flask_admin/contrib/sqla/validators.py
flask_admin/contrib/sqla/view.py
flask_admin/contrib/sqla/widgets.py
flask_admin/form/__init__.py
flask_admin/form/fields.py
flask_admin/form/rules.py
flask_admin/form/upload.py
flask_admin/form/validators.py
flask_admin/form/widgets.py
flask_admin/model/__init__.py
flask_admin/model/ajax.py
flask_admin/model/base.py
flask_admin/model/fields.py
flask_admin/model/filters.py
flask_admin/model/form.py
flask_admin/model/helpers.py
flask_admin/model/template.py
flask_admin/model/typefmt.py
flask_admin/model/widgets.py
flask_admin/static/admin/css/bootstrap2/admin.css
flask_admin/static/admin/css/bootstrap2/rediscli.css
flask_admin/static/admin/css/bootstrap3/admin.css
