Metadata-Version: 2.1
Name: Flask-Admix
Version: 1.6.1.1
Summary: Simple and extensible admin interface framework for Flask
Home-page: https://github.com/flask-admix/flask-admix/
Author: Flask-Admin team plus contributors
License: BSD
Platform: any
Classifier: Development Status :: 4 - Beta
Classifier: Environment :: Web Environment
Classifier: Intended Audience :: Developers
Classifier: License :: OSI Approved :: BSD License
Classifier: Operating System :: OS Independent
Classifier: Programming Language :: Python
Classifier: Topic :: Software Development :: Libraries :: Python Modules
Classifier: Programming Language :: Python :: 3.8
Classifier: Programming Language :: Python :: 3.9
Classifier: Programming Language :: Python :: 3.10
Classifier: Programming Language :: Python :: 3.11
Classifier: Programming Language :: Python :: 3.12
Requires-Python: >=3.8
License-File: LICENSE
License-File: NOTICE
License-File: AUTHORS
Requires-Dist: Flask>=1.1.1
Requires-Dist: wtforms>=3.1.0
Provides-Extra: aws
Requires-Dist: boto; extra == "aws"
Provides-Extra: azure
Requires-Dist: azure-storage-blob; extra == "azure"
